spcs_instruments/__init__.py
spcs_instruments/cli.py
spcs_instruments/spcs_instruments_utils.py
spcs_instruments/instruments/C8855_photon_counter_driver.py
spcs_instruments/instruments/__init__.py
spcs_instruments/instruments/keithley_2400_driver.py
spcs_instruments/instruments/siglent_sds_2352xe_driver.py
spcs_instruments/instruments/spcs_mixed_signal_switch_box_driver.py
spcs_instruments/instruments/srs830_lockin_amplifier_driver.py
spcs_instruments/instruments/test_daq.py
spcs_instruments/instruments/cryostats/__init__.py
spcs_instruments/instruments/cryostats/scryostation_driver.py
spcs_instruments/instruments/cryostats/test_cryostat.py
spcs_instruments/instruments/cryostats/montana_support/README.md
spcs_instruments/instruments/cryostats/montana_support/__init__.py
spcs_instruments/instruments/cryostats/montana_support/genericcryostat.py
spcs_instruments/instruments/cryostats/montana_support/instrument.py
spcs_instruments/instruments/cryostats/montana_support/mirs_helpers.py
spcs_instruments/instruments/cryostats/montana_support/scryostation.py
spcs_instruments/instruments/cryostats/montana_support/ssh_tunnel.py
spcs_instruments/instruments/lasers/PTI_GL100_dye_laser_driver.py
spcs_instruments/instruments/lasers/__init__.py
spcs_instruments/instruments/spectrometers/Horiba_iHR550_spectrometer_driver.py
spcs_instruments/instruments/spectrometers/__init__.py
spcs_instruments/instruments/spectrometers/oceanoptics_driver.py
spcs_instruments/instruments/spectrometers/test_spectrometer.py
spcs_instruments-0.9.2.dist-info/METADATA
spcs_instruments-0.9.2.dist-info/WHEEL
spcs_instruments-0.9.2.dist-info/entry_points.txt
spcs_instruments-0.9.2.dist-info/RECORD
