Metadata-Version: 2.4
Name: spcs-instruments
Version: 0.9.2
Summary: A experiment manager and instrument control library written in Python and Rust
Author-email: Jamin Martin <jamin.martin1@gmail.com>
Requires-Python: >=3.12
Requires-Dist: numpy>=2.0.0
Requires-Dist: pandas>=2.2.3
Requires-Dist: polars>=1.29.0
Requires-Dist: pyserial>=3.5
Requires-Dist: pyusb>=1.2.1
Requires-Dist: pyvisa-py>=0.7.2
Requires-Dist: pyvisa>=1.14.1
Requires-Dist: requests>=2.32.3
Requires-Dist: rex-pycli>=0.9.4
Requires-Dist: scipy>=1.14.0
Requires-Dist: seabreeze>=2.10.1
Requires-Dist: sshtunnel>=0.4.0
Requires-Dist: toml>=0.10.2
